flask_realip/__init__.py
flask_realip/real_ip.py
flask_realip-1.1.1.dist-info/licenses/LICENSE
flask_realip-1.1.1.dist-info/METADATA
flask_realip-1.1.1.dist-info/WHEEL
flask_realip-1.1.1.dist-info/top_level.txt
flask_realip-1.1.1.dist-info/RECORD
