Metadata-Version: 2.4
Name: flask-realip
Version: 1.1.1
Summary: Flask extension to get real IP addresses behind proxies
Author-email: TN3W <tn3w@protonmail.com>
License-Expression: Apache-2.0
Project-URL: Homepage, https://github.com/tn3w/flask-realip
Project-URL: Documentation, https://github.com/tn3w/flask-realip
Project-URL: Repository, https://github.com/tn3w/flask-realip.git
Project-URL: Issues, https://github.com/tn3w/flask-realip/issues
Classifier: Development Status :: 5 - Production/Stable
Classifier: Environment :: Web Environment
Classifier: Framework :: Flask
Classifier: Intended Audience :: Developers
Classifier: Operating System :: OS Independent
Classifier: Programming Language :: Python
Classifier: Programming Language :: Python :: 3
Classifier: Programming Language :: Python :: 3.9
Classifier: Programming Language :: Python :: 3.10
Classifier: Programming Language :: Python :: 3.11
Classifier: Programming Language :: Python :: 3.12
Classifier: Programming Language :: Python :: 3.13
Classifier: Topic :: Internet :: WWW/HTTP :: Dynamic Content
Classifier: Topic :: Software Development :: Libraries :: Python Modules
Requires-Python: >=3.6
License-File: LICENSE
Requires-Dist: Flask
Requires-Dist: netaddr
Dynamic: license-file
